README.md
setup.py
flask_test_requests_client.egg-info/PKG-INFO
flask_test_requests_client.egg-info/SOURCES.txt
flask_test_requests_client.egg-info/dependency_links.txt
flask_test_requests_client.egg-info/not-zip-safe
flask_test_requests_client.egg-info/requires.txt
flask_test_requests_client.egg-info/top_level.txt
frtc/__init__.py