Metadata-Version: 1.0
Name: flask-test-requests-client
Version: 0.2.0
Summary: A Flask test client which replicates the requests interface.
Home-page: http://github.com/jwg4/flask-test-requests-client
Author: Jack Grahl
Author-email: jack.grahl@gmail.com
License: MIT
Platform: UNKNOWN
